src/__init__.py
src/__main__.py
src/ast.py
src/interpreter.py
src/lexer.py
src/parser.py
mrt_lang-0.1.4.dist-info/LICENSE.txt
mrt_lang-0.1.4.dist-info/METADATA
mrt_lang-0.1.4.dist-info/WHEEL
mrt_lang-0.1.4.dist-info/entry_points.txt
mrt_lang-0.1.4.dist-info/top_level.txt
mrt_lang-0.1.4.dist-info/RECORD
