Metadata-Version: 2.1
Name: mrt-lang
Version: 0.1.4
Summary: MRT Programming Language - A modern, expressive programming language
Home-page: https://github.com/rithymeth/MRT
Author: MRT Team
Author-email: rithy1337@gmail.com
Keywords: programming language interpreter compiler
Classifier: Development Status :: 3 - Alpha
Classifier: Intended Audience :: Developers
Classifier: License :: OSI Approved :: MIT License
Classifier: Programming Language :: Python :: 3.10
Classifier: Programming Language :: Python :: 3.11
Classifier: Topic :: Software Development :: Interpreters
Requires-Python: >=3.10
License-File: LICENSE.txt
